hankey/__init__.py
hankey/abstract_dumper.py
hankey/abstract_remote.py
hankey/cloud_utils.py
hankey/command.py
hankey/daemon.py
hankey/dropbox.py
hankey/file.py
hankey/firebase.py
hankey/folder.py
hankey/hankey.py
hankey/main.py
hankey/service.py
hankey/tmp.py
hankey/utils.py
hankey-1.1.1.dist-info/METADATA
hankey-1.1.1.dist-info/WHEEL
hankey-1.1.1.dist-info/entry_points.txt
hankey-1.1.1.dist-info/top_level.txt
hankey-1.1.1.dist-info/RECORD
