Metadata-Version: 2.1
Name: hankey
Version: 1.1.1
Summary: Mr. Hankey The Christmas Poo
Home-page: https://github.com/amirmd76/hankey
Author: AmirMohammad Dehghan
Author-email: amirmd76@gmail.com
License: MIT
Platform: UNKNOWN
Classifier: License :: OSI Approved :: MIT License
Requires-Python: >= 3
Requires-Dist: firebase-admin
Requires-Dist: dropbox
